pytraverser.py
pytraverser-0.1.5.dist-info/licenses/LICENCE
pytraverser-0.1.5.dist-info/METADATA
pytraverser-0.1.5.dist-info/WHEEL
pytraverser-0.1.5.dist-info/entry_points.txt
pytraverser-0.1.5.dist-info/top_level.txt
pytraverser-0.1.5.dist-info/RECORD
