Metadata-Version: 2.4
Name: pytraverser
Version: 0.1.5
Summary: A terminal file tree traverser.
Author-email: Josh Stillerman <jas@mit.edu>
Project-URL: Homepage, https://github.com/you/pytraverser
Project-URL: Repository, https://github.com/you/pytraverser
Requires-Python: >=3.8
License-File: LICENCE
Requires-Dist: linkify-it-py>=2.0.3
Requires-Dist: markdown-it-py>=4.0.0
Requires-Dist: mdit-py-plugins>=0.5.0
Requires-Dist: mdsthin>=1.6.1
Requires-Dist: mdurl>=0.1.2
Requires-Dist: numpy>=2.2.6
Requires-Dist: platformdirs>=4.4.0
Requires-Dist: Pygments>=2.19.2
Requires-Dist: rich>=14.1.0
Requires-Dist: textual>=6.1.0
Requires-Dist: typing_extensions>=4.15.0
Requires-Dist: uc-micro-py>=1.0.3
Dynamic: license-file
